{
  "expo": {
    "name": "project",
    "slug": "project",
    "version": "1.0.0",
    "orientation": "portrait",
    "icon": "./assets/images/icon.png",
    "userInterfaceStyle": "light",
    "backgroundColor": "#ffffff",
    "newArchEnabled": true,
    "splash": {
      "image": "./assets/images/splash-icon.png",
      "resizeMode": "contain",
      "backgroundColor": "#ffffff"
    },
    "ios": {
      "supportsTablet": true
    },
    "android": {
      "adaptiveIcon": {
        "foregroundImage": "./assets/images/adaptive-icon.png",
        "backgroundColor": "#ffffff"
      },
      "edgeToEdgeEnabled": true
    },
    "web": {
      "favicon": "./assets/images/favicon.png"
    },
    "plugins": [
      [
        "expo-font",
        {
          "fonts": [
            "./assets/fonts/Exo400.ttf",
            "./assets/fonts/Exo500.ttf",
            "./assets/fonts/Exo600.ttf",
            "./assets/fonts/Exo700.ttf"
          ]
        }
      ],
      [
        "expo-location",
        {
          "locationAlwaysAndWhenInUsePermission": "Allow $(PRODUCT_NAME) to use your location."
        }
      ],
      "expo-router"
    ],
    "scheme": "social"
  }
}
